Degree_Audit/__init__.py
Degree_Audit/auditor.py
Degree_Audit/templates/audit.html
Degree_Audit/templates/macros.html
Degree_Audit-0.1.dist-info/METADATA
Degree_Audit-0.1.dist-info/WHEEL
Degree_Audit-0.1.dist-info/top_level.txt
Degree_Audit-0.1.dist-info/RECORD
