Metadata-Version: 2.1
Name: Degree-Audit
Version: 0.1
Summary: Degree Auditor for Northern Kentucky University MSCS degree
Home-page: UNKNOWN
Author: Kathleen Edwards
Author-email: UNKNOWN
License: UNKNOWN
Platform: UNKNOWN
